microwink/__init__.py
microwink/common.py
microwink/py.typed
microwink/seg.py
microwink-0.0.4.dist-info/METADATA
microwink-0.0.4.dist-info/WHEEL
microwink-0.0.4.dist-info/licenses/LICENSE
microwink-0.0.4.dist-info/RECORD
