Metadata-Version: 2.4
Name: microwink
Version: 0.0.4
Summary: Lightweight instance segmentation of card IDs
Project-URL: Repository, https://github.com/cospectrum/microwink
Author-email: cospectrum <severinalexeyv@gmail.com>
License: Apache-2.0
License-File: LICENSE
Requires-Python: >=3.10
Requires-Dist: numpy>=2.2.0
Requires-Dist: onnxruntime>=1.20.1
Requires-Dist: pillow>=11.0.0
